setup.py
zcy_test/__init__.py
zcy_test/test1.py
zcy_test.egg-info/PKG-INFO
zcy_test.egg-info/SOURCES.txt
zcy_test.egg-info/dependency_links.txt
zcy_test.egg-info/entry_points.txt
zcy_test.egg-info/top_level.txt