Metadata-Version: 1.0
Name: zcy-test
Version: 0.0.5
Summary: My test module
Home-page: http://www.csdn.net
Author: zcy
Author-email: zcy19941015@qq.com
License: LGPL
Platform: UNKNOWN
